[{"User":"admin","admin":true,"id":"f20bf43d-9184-4fea-a6d3-7847046030a1","name":"Juan Manuel","surname":"Sanjurjo","email":"admin1","password":"admin1"},{"User":"admin","admin":true,"id":"7011c5ba-21b0-45cb-bebe-ae961f8efe8c","name":"Mariano","surname":"Fernandez","email":"admin2","password":"admin2"},{"User":"user","id":"c59865d9-c3fc-4cb2-88ae-42aeb0c08188","name":"JUAN MANUEL","surname":"SANJURJO","dni":"34883649","age":"32","email":"juanma@hotmail.com","password":"Juanma123"},{"User":"user","id":"b7bafb16-449f-4208-83a2-e3049ddef9e7","name":"MARIANO","surname":"FERNANDEZ","dni":"39645127","age":"28","email":"mariano@hotmail.com","password":"Mariano123"},{"User":"user","id":"9e31eec9-55fa-46ee-bb66-7adc1cfc4c37","name":"ROMINA","surname":"BRONCO","dni":"36987458","age":"37","email":"romina@live.com.ar","password":"RomiBronco99"},{"User":"user","id":"e013772d-3200-445e-acc2-b81e1069f244","name":"JULIO","surname":"VERNE","dni":"45678912","age":"99","email":"verne@hotmail.com","password":"Vernejulio12"},{"User":"user","id":"3cd3deff-73e7-41d8-83f2-5cbf38961fa4","name":"JOSE MATIAS","surname":"PEREZ","dni":"34512789","age":"31","email":"matias@gmail.com","password":"Matias123456"},{"User":"user","id":"b5a32c6f-c2f1-4262-bf19-a197b7c03278","name":"RODRIGO","surname":"ORTIGOZA","dni":"24568974","age":"49","email":"rodrigo@outlook.com","password":"Rodrigoortigozal12"},{"User":"user","id":"5581de51-dfb3-467b-83e5-c80998f4c919","name":"SERGIO PATRICIO","surname":"GONZALEZ ORTIGOZA","dni":"23561427","age":"54","email":"sergio@live.com.ar","password":"sergioPatricio123"},{"User":"user","id":"90b914b0-bc9b-4e0b-9323-aef511b6afc9","name":"MARINA JULIETA","surname":"DI GIORGIO","dni":"45214569","age":"24","email":"marina@live.com.ar","password":"marinaDigiorgio123"},{"User":"user","id":"c426c989-f55b-4573-a044-933d2c6b9e9b","name":"ANA INES","surname":"VERANO","dni":"35124578","age":"31","email":"ana@live.com.ar","password":"anaVerano123"},{"User":"user","id":"2517be58-9de6-48e7-a7b0-08265defee0a","name":"JULIETA","surname":"GIULIANO","dni":"33157856","age":"33","email":"julieta@live.com.ar","password":"JulieTaG123"},{"User":"user","id":"f8125bbb-f28c-450d-9da5-bf5012844ace","name":"CINTIA","surname":"LOZADA","dni":"17895462","age":"45","email":"cintia@live.com.ar","password":"cinLozada27"},{"User":"user","id":"65219285-ac46-411f-9c63-49db25da48da","name":"GABRIELA","surname":"DI SCALA","dni":"39564872","age":"34","email":"gabriela@live.com.ar","password":"20Gabriela"},{"User":"user","id":"ee5508fc-25d8-4253-bbcf-8fc11f70cc94","name":"CAMILA","surname":"ROMANO","dni":"14563256","age":"55","email":"camila@live.com.ar","password":"camiLA4589"},{"User":"user","id":"2123fd9d-f1a6-407c-a52f-91665e679668","name":"MICAELA","surname":"VERGARA MOLINA","dni":"251457985","age":"40","email":"micaela@live.com.ar","password":"MicaMolina40"},{"User":"user","id":"b0927166-3ed8-4083-a601-37da7af79e52","name":"MARCOS","surname":"LABRA","dni":"35145287","age":"30","email":"marcos@live.com.ar","password":"marcosLa50"}]